nicaviz/__init__.py
nicaviz/dataframe_visualizer.py
nicaviz/pandas_reduce_memory.py
nicaviz/python_utils.py
nicaviz/processsing/__init__.py
nicaviz/processsing/nlp.py
nicaviz/processsing/normalisation.py
nicaviz-0.1.4.dist-info/LICENSE
nicaviz-0.1.4.dist-info/METADATA
nicaviz-0.1.4.dist-info/WHEEL
nicaviz-0.1.4.dist-info/top_level.txt
nicaviz-0.1.4.dist-info/RECORD
