Metadata-Version: 2.1
Name: nicaviz
Version: 0.1.4
Summary: Python Visualization Package
Home-page: https://github.com/nicapotato/nicaviz
Author: nicapotato
Author-email: nick.brooks27@gmail.com
License: UNKNOWN
Platform: UNKNOWN
Classifier: Programming Language :: Python :: 3
Classifier: License :: OSI Approved :: MIT License
Classifier: Operating System :: OS Independent
Requires-Python: >=3.5
Requires-Dist: numpy (>=1.14.2)
Requires-Dist: pandas (>=0.23.4)
Requires-Dist: python-dateutil (>=2.8.1)
Requires-Dist: seaborn (>=0.9.0)
Requires-Dist: statsmodels (>=0.9.0)
Requires-Dist: wordcloud (>=1.8.1)
